essence_wars/__init__.py
essence_wars/_core.cpython-310-darwin.so
essence_wars/agents/__init__.py
essence_wars/agents/alphazero.py
essence_wars/agents/networks.py
essence_wars/agents/ppo.py
essence_wars/analysis/__init__.py
essence_wars/analysis/aggregator.py
essence_wars/analysis/dashboard.py
essence_wars/analysis/parse_log.py
essence_wars/analysis/performance_dashboard.py
essence_wars/analysis/research_dashboard.py
essence_wars/analysis/validation_cli.py
essence_wars/analysis/visualize.py
essence_wars/benchmark/__init__.py
essence_wars/benchmark/agents.py
essence_wars/benchmark/api.py
essence_wars/benchmark/elo.py
essence_wars/benchmark/metrics.py
essence_wars/data/__init__.py
essence_wars/data/dataset.py
essence_wars/env.py
essence_wars/hub.py
essence_wars/infra/__init__.py
essence_wars/infra/experiment.py
essence_wars/parallel_env.py
essence_wars/training/__init__.py
essence_wars/viz/__init__.py
essence_wars/viz/ascii_renderer.py
essence_wars-0.7.0.dist-info/METADATA
essence_wars-0.7.0.dist-info/WHEEL
essence_wars-0.7.0.dist-info/RECORD
