Metadata-Version: 2.4
Name: essence-wars
Version: 0.7.0
Classifier: Development Status :: 4 - Beta
Classifier: Intended Audience :: Science/Research
Classifier: License :: OSI Approved :: MIT License
Classifier: Programming Language :: Python :: 3
Classifier: Programming Language :: Python :: 3.10
Classifier: Programming Language :: Python :: 3.11
Classifier: Programming Language :: Python :: 3.12
Classifier: Programming Language :: Rust
Classifier: Topic :: Scientific/Engineering :: Artificial Intelligence
Classifier: Topic :: Games/Entertainment :: Board Games
Requires-Dist: numpy>=1.24.0
Requires-Dist: gymnasium>=0.29.0
Requires-Dist: essence-wars[train,analysis,hub,pettingzoo] ; extra == 'all'
Requires-Dist: pandas>=2.2.0 ; extra == 'analysis'
Requires-Dist: matplotlib>=3.8.0 ; extra == 'analysis'
Requires-Dist: seaborn>=0.13.0 ; extra == 'analysis'
Requires-Dist: plotly>=5.18.0 ; extra == 'analysis'
Requires-Dist: jinja2>=3.1.0 ; extra == 'analysis'
Requires-Dist: rich>=13.7.0 ; extra == 'analysis'
Requires-Dist: pytest>=7.0.0 ; extra == 'dev'
Requires-Dist: pytest-cov>=4.0.0 ; extra == 'dev'
Requires-Dist: ruff>=0.1.0 ; extra == 'dev'
Requires-Dist: mypy>=1.0.0 ; extra == 'dev'
Requires-Dist: huggingface-hub>=0.20.0 ; extra == 'hub'
Requires-Dist: pettingzoo>=1.24.0 ; extra == 'pettingzoo'
Requires-Dist: torch>=2.0.0 ; extra == 'train'
Requires-Dist: tensorboard>=2.14.0 ; extra == 'train'
Requires-Dist: wandb>=0.16.0 ; extra == 'train'
Requires-Dist: tqdm>=4.66.0 ; extra == 'train'
Provides-Extra: all
Provides-Extra: analysis
Provides-Extra: dev
Provides-Extra: hub
Provides-Extra: pettingzoo
Provides-Extra: train
Summary: High-performance card game environment for reinforcement learning research
Keywords: reinforcement-learning,game,gymnasium,ai,mcts,card-game,pettingzoo
Author: Christian Wissmann
License: MIT
Requires-Python: >=3.10
Project-URL: Documentation, https://christianwissmann85.github.io/essence-wars/
Project-URL: Homepage, https://github.com/christianwissmann85/essence-wars
Project-URL: Issues, https://github.com/christianwissmann85/essence-wars/issues
Project-URL: Repository, https://github.com/christianwissmann85/essence-wars
